pixtreme_core/__init__.py
pixtreme_core/constants.py
pixtreme_core/py.typed
pixtreme_core/types.py
pixtreme_core/color/__init__.py
pixtreme_core/color/bgr.py
pixtreme_core/color/grayscale.py
pixtreme_core/color/hsv.py
pixtreme_core/color/uyvy422.py
pixtreme_core/color/uyvy422_ndi.py
pixtreme_core/color/ycbcr.py
pixtreme_core/color/yuv420.py
pixtreme_core/color/yuv422p10le.py
pixtreme_core/color/lut/__init__.py
pixtreme_core/color/lut/apply_lut.py
pixtreme_core/color/lut/read_lut.py
pixtreme_core/io/__init__.py
pixtreme_core/io/imdecode.py
pixtreme_core/io/imencode.py
pixtreme_core/io/imread.py
pixtreme_core/io/imshow.py
pixtreme_core/io/imwrite.py
pixtreme_core/transform/__init__.py
pixtreme_core/transform/affine.py
pixtreme_core/transform/resize.py
pixtreme_core/transform/stack.py
pixtreme_core/transform/subsample.py
pixtreme_core/transform/subsample_flattened.py
pixtreme_core/transform/subsample_optimized_v2.py
pixtreme_core/transform/tile.py
pixtreme_core/transform/interpolation/area.py
pixtreme_core/transform/interpolation/bicubic.py
pixtreme_core/transform/interpolation/bilinear.py
pixtreme_core/transform/interpolation/lanczos.py
pixtreme_core/transform/interpolation/mitchell.py
pixtreme_core/transform/interpolation/nearest.py
pixtreme_core/utils/__init__.py
pixtreme_core/utils/device.py
pixtreme_core/utils/dlpack.py
pixtreme_core/utils/dtypes.py
pixtreme_core-0.8.6.dist-info/METADATA
pixtreme_core-0.8.6.dist-info/WHEEL
pixtreme_core-0.8.6.dist-info/licenses/LICENSE
pixtreme_core-0.8.6.dist-info/RECORD
