Metadata-Version: 2.4
Name: pixtreme-core
Version: 0.8.6
Summary: pixtreme-core: High-Performance GPU Image Processing Core Library
Project-URL: repository, https://github.com/sync-dev-org/pixtreme
Project-URL: issues, https://github.com/sync-dev-org/pixtreme/issues
Author-email: minamik <mia@sync.dev>
License-Expression: MIT
License-File: LICENSE
Classifier: Development Status :: 4 - Beta
Classifier: Environment :: GPU :: NVIDIA CUDA :: 12
Classifier: Intended Audience :: Developers
Classifier: License :: OSI Approved :: MIT License
Classifier: Operating System :: Microsoft :: Windows
Classifier: Operating System :: POSIX :: Linux
Classifier: Programming Language :: Python :: 3.12
Classifier: Programming Language :: Python :: 3.13
Classifier: Topic :: Multimedia :: Graphics
Classifier: Topic :: Software Development :: Libraries
Requires-Python: >=3.12
Requires-Dist: cupy-cuda12x>=13.4.1
Requires-Dist: numpy
Requires-Dist: nvidia-nvimgcodec-cu12[all]>=0.6.0
Requires-Dist: opencv-python
Requires-Dist: openexr>=3.3.3
Requires-Dist: platformdirs>=4.0.0
